<?xml version="1.0" encoding="UTF-8"?>
<!--###################################################################################
		Lake of Constance Hangar :: M.Kraus
		Boeing 707 for Flightgear Septemper 2013
		This file is licenced under the terms of the GNU General Public Licence V2 or later
		###################################################################################
-->
<PropertyList> 
    <title>VII. Before taxiing or takeoff</title>    
	<item>
      <name>VI. After startup engines</name>
      <value>COMPLETED</value>
    </item>
	
    <item>
      <name>DOORS</name>
      <value>CLOSED</value>
		<marker>
		    <x-m>-17.1744</x-m>
		    <y-m>0.7868</y-m>
		    <z-m>1.1405</z-m>
		    <scale>5.0000</scale>
		</marker>
      <condition>
		<and>
	        <equals>
	          <property>/instrumentation/doors/pilotwin/position-norm</property>
	          <value>0</value>
	        </equals>
	        <equals>
	          <property>/instrumentation/doors/copilotwin/position-norm</property>
	          <value>0</value>
	        </equals>
	        <equals>
	          <property>/instrumentation/doors/pasfront/position-norm</property>
	          <value>0</value>
	        </equals>
	        <equals>
	          <property>/instrumentation/doors/pasrear/position-norm</property>
	          <value>0</value>
	        </equals>
	        <equals>
	          <property>/instrumentation/doors/nose/position-norm</property>
	          <value>0</value>
	        </equals>
	        <equals>
	          <property>/instrumentation/doors/cargo/position-norm</property>
	          <value>0</value>
	        </equals>
	        <equals>
	          <property>/instrumentation/doors/belly/position-norm</property>
	          <value>0</value>
	        </equals>
	        <equals>
	          <property>/instrumentation/doors/refuel-boom/position-norm</property>
	          <value>0</value>
	        </equals>
		</and>
      </condition>      
	  <binding>
        <command>property-assign</command>
        <property>/instrumentation/doors/refuel-boom/position-norm</property>
        <value>0</value>
      </binding>     
	  <binding>
        <command>property-assign</command>
        <property>/instrumentation/doors/belly/position-norm</property>
        <value>0</value>
      </binding>     
	  <binding>
        <command>property-assign</command>
        <property>/instrumentation/doors/cargo/position-norm</property>
        <value>0</value>
      </binding>     
	  <binding>
        <command>property-assign</command>
        <property>/instrumentation/doors/nose/position-norm</property>
        <value>0</value>
      </binding>     
	  <binding>
        <command>property-assign</command>
        <property>/instrumentation/doors/pasrear/position-norm</property>
        <value>0</value>
      </binding>     
	  <binding>
        <command>property-assign</command>
        <property>/instrumentation/doors/pasfront/position-norm</property>
        <value>0</value>
      </binding>     
	  <binding>
        <command>property-assign</command>
        <property>/instrumentation/doors/copilotwin/position-norm</property>
        <value>0</value>
      </binding>     
	  <binding>
        <command>property-assign</command>
        <property>/instrumentation/doors/pilotwin/position-norm</property>
        <value>0</value>
      </binding>
    </item>
	
	<item>
		<name>AIR COMPRESSOR ENG 2</name>
		<value>ON</value>
		<marker>
		    <x-m>-17.4926</x-m>
		    <y-m>0.5843</y-m>
		    <z-m>1.4653</z-m>
		    <scale>1.4298</scale>
		</marker>
		<condition>
		  <greater-than>
		    <property>/b707/air-conditioning/compressor-rpm[0]</property>
		    <value>95</value>
		  </greater-than>
		</condition>		
		<binding>
            <command>nasal</command>
            <script>b707.air_compressor(0);</script>
		</binding>    
	    <binding>
	      <command>property-toggle</command>
	      <property>/sim/sound/switch1</property>
	    </binding>
	</item>

	<item>
		<name>AIR COMPRESSOR ENG 3</name>
		<value>ON</value>
		<marker>
		    <x-m>-17.4372</x-m>
		    <y-m>0.5843</y-m>
		    <z-m>1.4653</z-m>
		    <scale>1.4298</scale>
		</marker>
		<condition>
		  <greater-than>
		    <property>/b707/air-conditioning/compressor-rpm[1]</property>
		    <value>95</value>
		  </greater-than>
		</condition>		
		<binding>
            <command>nasal</command>
            <script>b707.air_compressor(1);</script>
		</binding>    
	    <binding>
	      <command>property-toggle</command>
	      <property>/sim/sound/switch1</property>
	    </binding>
	</item>

	<item>
		<name>AIR COMPRESSOR ENG 4</name>
		<value>ON</value>
		<marker>
		    <x-m>-17.3802</x-m>
		    <y-m>0.5843</y-m>
		    <z-m>1.4653</z-m>
		    <scale>1.4298</scale>
		</marker>
		<condition>
		  <greater-than>
		    <property>/b707/air-conditioning/compressor-rpm[2]</property>
		    <value>95</value>
		  </greater-than>
		</condition>		
		<binding>
            <command>nasal</command>
            <script>b707.air_compressor(2);</script>
		</binding>    
	    <binding>
	      <command>property-toggle</command>
	      <property>/sim/sound/switch1</property>
	    </binding>
	</item>
	
	<item>
		<name>FUEL HEATERS ICING 1</name>
		<value>ON</value>
		<marker>
		    <x-m>-17.8207</x-m>
		    <y-m>0.7488</y-m>
		    <z-m>0.8000</z-m>
		    <scale>2.3884</scale>
		</marker>
		<condition>
		  <equals>
		    <property>/b707/fuel/heater[0]</property>
		    <value>1</value>
		  </equals>
		</condition>		
		<binding>
		  <command>property-assign</command>
		  <property>/b707/fuel/heater[0]</property>
		  <value>1</value>
		</binding>    
	    <binding>
	      <command>property-toggle</command>
	      <property>/sim/sound/switch1</property>
	    </binding>
	</item>
	
	<item>
		<name>FUEL HEATERS ICING 2</name>
		<value>ON</value>
		<marker>
		    <x-m>-17.7570</x-m>
		    <y-m>0.7488</y-m>
		    <z-m>0.8000</z-m>
		    <scale>2.3884</scale>
		</marker>
		<condition>
		  <equals>
		    <property>/b707/fuel/heater[1]</property>
		    <value>1</value>
		  </equals>
		</condition>		
		<binding>
		  <command>property-assign</command>
		  <property>/b707/fuel/heater[1]</property>
		  <value>1</value>
		</binding>    
	    <binding>
	      <command>property-toggle</command>
	      <property>/sim/sound/switch1</property>
	    </binding>
	</item>
			
	<item>
		<name>FUEL HEATERS ICING 3</name>
		<value>ON</value>
		<marker>
		    <x-m>-17.7091</x-m>
		    <y-m>0.7488</y-m>
		    <z-m>0.8000</z-m>
		    <scale>2.3884</scale>
		</marker>
		<condition>
		  <equals>
		    <property>/b707/fuel/heater[2]</property>
		    <value>1</value>
		  </equals>
		</condition>		
		<binding>
		  <command>property-assign</command>
		  <property>/b707/fuel/heater[2]</property>
		  <value>1</value>
		</binding>    
	    <binding>
	      <command>property-toggle</command>
	      <property>/sim/sound/switch1</property>
	    </binding>
	</item>
		
	<item>
		<name>FUEL HEATERS ICING 4</name>
		<value>ON</value>
		<marker>
		    <x-m>-17.6512</x-m>
		    <y-m>0.7488</y-m>
		    <z-m>0.8000</z-m>
		    <scale>2.3884</scale>
		</marker>
		<condition>
		  <equals>
		    <property>/b707/fuel/heater[3]</property>
		    <value>1</value>
		  </equals>
		</condition>		
		<binding>
		  <command>property-assign</command>
		  <property>/b707/fuel/heater[3]</property>
		  <value>1</value>
		</binding>    
	    <binding>
	      <command>property-toggle</command>
	      <property>/sim/sound/switch1</property>
	    </binding>
	</item>
		
	<item>
		<name>WINDOW HEAT F/O</name>
		<value>LOW</value>
		<marker>
		    <x-m>-18.6570</x-m>
		    <y-m>0.2603</y-m>
		    <z-m>1.3033</z-m>
		    <scale>1.5289</scale>
		</marker>
		<condition>
		  <greater-than>
		    <property>/b707/anti-ice/window-heat-fo-switch</property>
		    <value>0</value>
		  </greater-than>
		</condition>		
		<binding>
		  <command>property-assign</command>
		  <property>/b707/anti-ice/window-heat-fo-switch</property>
		  <value>1</value>
		</binding>    
	    <binding>
	      <command>property-toggle</command>
	      <property>/sim/sound/switch1</property>
	    </binding>
	</item>
	
	<item>
		<name>WINDOW HEAT CAP</name>
		<value>LOW</value>
		<marker>
		    <x-m>-18.6570</x-m>
		    <y-m>0.1860</y-m>
		    <z-m>1.3033</z-m>
		    <scale>1.5289</scale>
		</marker>
		<condition>
		  <greater-than>
		    <property>/b707/anti-ice/window-heat-cap-switch</property>
		    <value>0</value>
		  </greater-than>
		</condition>		
		<binding>
		  <command>property-assign</command>
		  <property>/b707/anti-ice/window-heat-cap-switch</property>
		  <value>1</value>
		</binding>    
	    <binding>
	      <command>property-toggle</command>
	      <property>/sim/sound/switch1</property>
	    </binding>
	</item>
	
	<item>
		<name>YAW DAMPER</name>
		<value>OFF</value>
		<marker>
		    <x-m>-18.7190</x-m>
		    <y-m>0.1331</y-m>
		    <z-m>1.2793</z-m>
		    <scale>2.0909</scale>
		</marker>
		<condition>
		  <equals>
		    <property>/autopilot/internal/yaw-damper</property>
		    <value>0</value>
		  </equals>
		</condition>		
		<binding>
		  <command>property-assign</command>
		  <property>/autopilot/internal/yaw-damper</property>
		  <value>0</value>
		</binding>    
	    <binding>
	      <command>property-toggle</command>
	      <property>/sim/sound/switch1</property>
	    </binding>
	</item>
	
    <item>
      <name>COMPASS CONTROLLER 2</name>
      <value>SET LATITUDE / DG</value>
	  <marker>
	      <x-m>-18.6107</x-m>
	      <y-m>0.1008</y-m>
	      <z-m>1.3223</z-m>
	      <scale>1.8430</scale>
	  </marker>
      <condition>
		  <and>
	        <not><property>/instrumentation/compass-control[1]/mag</property></not>
			<property>/instrumentation/compass-control[1]/justify</property>
		  </and>
      </condition>
      <binding>
        <command>property-assign</command>
        <property>/instrumentation/compass-control[1]/mag</property>
        <value>0</value>
      </binding> 
      <binding>
        <command>nasal</command>
        <script>
		    <![CDATA[
        	var latP = getprop("/position/latitude-deg") or 0;
			if(latP < 0) setprop("/instrumentation/compass-control[1]/lat-knob", 1);
			latP = abs(int(latP));
			setprop("/instrumentation/compass-control[1]/lat-turn", latP);
		    ]]>
        </script>
      </binding>        
	  <binding>
	    <command>property-toggle</command>
	    <property>/sim/sound/switch1</property>
	  </binding>
    </item>
	
	<item>
		<name>OXYGEN</name>
		<value>NORM</value>
		<marker>
		    <x-m>-18.5446</x-m>
		    <y-m>0.0017</y-m>
		    <z-m>1.3430</z-m>
		    <scale>1.5289</scale>
		</marker>
		<condition>
		  <equals>
		    <property>/b707/emergency/oxygen-switch</property>
		    <value>2</value>
		  </equals>
		</condition>		
		<binding>
		  <command>property-assign</command>
	      <property>/b707/emergency/oxygen-switch</property>
	      <value>2</value>
		</binding>    
	    <binding>
	      <command>property-toggle</command>
	      <property>/sim/sound/switch1</property>
	    </binding>
	</item>
	
    <item>
      <name>COMPASS CONTROLLER 1</name>
      <value>SET LATITUDE / DG</value>
	  <marker>
	      <x-m>-18.6107</x-m>
	      <y-m>-0.0893</y-m>
	      <z-m>1.3223</z-m>
	      <scale>1.8430</scale>
	  </marker>
      <condition>
		  <and>
	        <not><property>/instrumentation/compass-control[0]/mag</property></not>
			<property>/instrumentation/compass-control[0]/justify</property>
		  </and>
      </condition>
      <binding>
        <command>property-assign</command>
        <property>/instrumentation/compass-control[0]/mag</property>
        <value>0</value>
      </binding> 
      <binding>
        <command>nasal</command>
        <script>
		    <![CDATA[
        	var latP = getprop("/position/latitude-deg") or 0;
			if(latP < 0) setprop("/instrumentation/compass-control[0]/lat-knob", 1);
			latP = abs(int(latP));
			setprop("/instrumentation/compass-control[0]/lat-turn", latP);
		    ]]>
        </script>
      </binding>        
	  <binding>
	    <command>property-toggle</command>
	    <property>/sim/sound/switch1</property>
	  </binding>
    </item>
			
    <item>
      <name>TRANSPONDER</name>
      <value>ON</value>
	  <marker>
	      <x-m>-18.4529</x-m>
	      <y-m>-0.2537</y-m>
	      <z-m>1.3818</z-m>
	      <scale>1.4463</scale>
	  </marker>
      <condition>
        <equals>
          <property>/instrumentation/transponder/inputs/knob-mode</property>
          <value>4</value>
        </equals>
      </condition>
      <binding>
        <command>property-assign</command>
        <property>/instrumentation/transponder/inputs/knob-mode</property>
        <value>4</value>
      </binding>        
	  <binding>
	    <command>property-toggle</command>
	    <property>/sim/sound/switch1</property>
	  </binding>
    </item>
		
	<item>
		<name>WING ANTI ICE</name>
		<value>ON</value>
		<marker>
		    <x-m>-18.5041</x-m>
		    <y-m>-0.2017</y-m>
		    <z-m>1.3496</z-m>
		    <scale>1.7107</scale>
		</marker>
		<condition>
		  <equals>
		    <property>/b707/anti-ice/switch</property>
		    <value>2</value>
		  </equals>
		</condition>		
		<binding>
		  <command>property-assign</command>
	   	  <property>/b707/anti-ice/switch</property>
	      <value>2</value>
		</binding>    
	    <binding>
	      <command>property-toggle</command>
	      <property>/sim/sound/switch1</property>
	    </binding>
	</item>	
		
	<item>
		<name>NACELLE ANTI ICE</name>
		<value>ON</value>
		<marker>
		    <x-m>-18.5777</x-m>
		    <y-m>-0.2322</y-m>
		    <z-m>1.3124</z-m>
		    <scale>2.5868</scale>
		</marker>
		<condition>
		  <equals>
		    <property>/b707/anti-ice/engine-inlet[0]</property>
		    <value>1</value>
		  </equals>
		  <equals>
		    <property>/b707/anti-ice/engine-inlet[1]</property>
		    <value>1</value>
		  </equals>
		  <equals>
		    <property>/b707/anti-ice/engine-inlet[2]</property>
		    <value>1</value>
		  </equals>
		  <equals>
		    <property>/b707/anti-ice/engine-inlet[3]</property>
		    <value>1</value>
		  </equals>
		</condition>		
		<binding>
		  <command>property-assign</command>
	   	  <property>/b707/anti-ice/engine-inlet[0]</property>
	      <value>1</value>
		</binding> 
		<binding>
		  <command>property-assign</command>
	   	  <property>/b707/anti-ice/engine-inlet[1]</property>
	      <value>1</value>
		</binding>  
		<binding>
		  <command>property-assign</command>
	   	  <property>/b707/anti-ice/engine-inlet[2]</property>
	      <value>1</value>
		</binding>  
		<binding>
		  <command>property-assign</command>
	   	  <property>/b707/anti-ice/engine-inlet[3]</property>
	      <value>1</value>
		</binding>     
	    <binding>
	      <command>property-toggle</command>
	      <property>/sim/sound/switch1</property>
	    </binding>
	</item>
	
	<item>
		<name>LEADING EDGE FLAPS</name>
		<value>PRESELECTED</value>
		<marker>
		    <x-m>-18.9107</x-m>
		    <y-m>0.1430</y-m>
		    <z-m>0.9612</z-m>
		    <scale>1.3636</scale>
		</marker>
		<condition>
		  <equals>
		    <property>/controls/special/slats-switch</property>
		    <value>1</value>
		  </equals>
		</condition>		
		<binding>
		  <command>property-assign</command>
		  <property>/controls/special/slats-switch</property>
		  <value>1</value>
		</binding>    
	    <binding>
	      <command>property-toggle</command>
	      <property>/sim/sound/switch1</property>
	    </binding>
	</item>
	
	<item>
		<name>FLAPS</name>
		<value>EXTEND</value>
		<marker>
		    <x-m>-18.9083</x-m>
		    <y-m>0.1248</y-m>
		    <z-m>0.8843</z-m>
		    <scale>4.1901</scale>
		</marker>
		<condition>
		  <greater-than>
		    <property>controls/flight/flaps</property>
		    <value>0</value>
		  </greater-than>
		</condition>		
		<binding>
		  <command>nasal</command>
		  <script>controls.flapsDown(1)</script>
		</binding>    
	    <binding>
	      <command>property-toggle</command>
	      <property>/sim/sound/switch1</property>
	    </binding>
	</item>

	<item>
		<name>SPEEDBRAKE LEVER</name>
		<value>FULL FORWARD</value>
		<condition>
		  <equals>
		    <property>/controls/flight/spoilers</property>
		    <value>0</value>
		  </equals>
		</condition>		
		<binding>
		  <command>property-assign</command>
		  <property>/controls/flight/spoilers</property>
		  <value>0</value>
		</binding>    
	    <binding>
	      <command>property-toggle</command>
	      <property>/sim/sound/switch1</property>
	    </binding>
	</item>	

	<item>
		<name>ALL TRIM WHEELS</name>
		<value>RESET</value>
		<condition>
			<and>
			  <equals>
			    <property>/controls/flight/elevator-trim</property>
			    <value>0</value>
			  </equals>
			  <equals>
			    <property>/controls/flight/rudder-trim</property>
			    <value>0</value>
			  </equals>
			  <equals>
			    <property>/controls/flight/aileron-trim</property>
			    <value>0</value>
			  </equals>
			</and>
		</condition>		
		<binding>
		  <command>nasal</command>
		  <script>b707.applyTrimWheels(0, 0);b707.applyTrimWheels(0, 1);b707.applyTrimWheels(0, 2);</script>
		</binding>       
	    <binding>
	      <command>property-toggle</command>
	      <property>/sim/sound/switch1</property>
	    </binding>
	</item>	

	<item>
		<name>EXTERIOR LIGHTS</name>
		<value>SET</value>
	</item>
		
	<item>
		<name>QNH</name>
		<value>SET</value>
	</item>
	
</PropertyList>